README.md
setup.cfg
setup.py
example_agent/__init__.py
example_agent/example_agent.py
example_agent.egg-info/PKG-INFO
example_agent.egg-info/SOURCES.txt
example_agent.egg-info/dependency_links.txt
example_agent.egg-info/not-zip-safe
example_agent.egg-info/top_level.txt