Metadata-Version: 2.1
Name: example-agent
Version: 1.0
Summary: This will return Sithumi's info.
